test_containers/__init__.py
test_containers/__main__.py
test_containers/application.py
test_containers/environments.py
test_containers/evaluator.py
test_containers/help.txt
test_containers/test.py
test_containers/utils.py
test_containers-0.1.10.dist-info/LICENSE.txt
test_containers-0.1.10.dist-info/METADATA
test_containers-0.1.10.dist-info/WHEEL
test_containers-0.1.10.dist-info/top_level.txt
test_containers-0.1.10.dist-info/RECORD
