Metadata-Version: 2.1
Name: test-containers
Version: 0.1.10
Summary: Test containers using yaml files for configuration.
Requires-Dist: PyYAML
Requires-Dist: docker
Requires-Dist: kubernetes
